setup.py
funniest1/__init__.py
funniest1.egg-info/PKG-INFO
funniest1.egg-info/SOURCES.txt
funniest1.egg-info/dependency_links.txt
funniest1.egg-info/not-zip-safe
funniest1.egg-info/top_level.txt