Metadata-Version: 1.0
Name: funniest1
Version: 0.1
Summary: The funniest joke in the world
Home-page: UNKNOWN
Author: Flying Circus
Author-email: UNKNOWN
License: MIT
Platform: UNKNOWN
